MANIFEST.in
README.md
setup.cfg
setup.py
src/marrs/__init__.py
src/marrs/android_manifest.py
src/marrs/app.py
src/marrs/consts.py
src/marrs/device.py
src/marrs/files.py
src/marrs/log.py
src/marrs/main.py
src/marrs/storage.py
src/marrs/utils.py
src/marrs.egg-info/PKG-INFO
src/marrs.egg-info/SOURCES.txt
src/marrs.egg-info/dependency_links.txt
src/marrs.egg-info/requires.txt
src/marrs.egg-info/top_level.txt
src/marrs/data/bundle.js
src/marrs/frida/__init__.py
src/marrs/frida/agent.py
src/marrs/frida/consts.py
src/marrs/frida/output_window_client.py
src/marrs/frida/output_window_server.py
src/marrs/frida/utils.py
src/marrs/frida/hooks/__init__.py
src/marrs/frida/hooks/hook.py
src/marrs/frida/hooks/hooks_manager.py
src/marrs/frida/wrappers/__init__.py
src/marrs/frida/wrappers/instance_factory.py
src/marrs/frida/wrappers/wclass.py
src/marrs/frida/wrappers/wconstructor.py
src/marrs/frida/wrappers/wfield.py
src/marrs/frida/wrappers/wmethod.py
src/marrs/frida/wrappers/instances/__init__.py
src/marrs/frida/wrappers/instances/warray.py
src/marrs/frida/wrappers/instances/winstance.py